Htraffick.py
Htraffick-0.0.1.dist-info/METADATA
Htraffick-0.0.1.dist-info/WHEEL
Htraffick-0.0.1.dist-info/entry_points.txt
Htraffick-0.0.1.dist-info/top_level.txt
Htraffick-0.0.1.dist-info/RECORD
