Metadata-Version: 2.1
Name: Htraffick
Version: 0.0.1
Summary: A package for scoring policies of Indian Trafficking Law
Home-page: https://github.com/sachan-37/Htraffick
Author: sana okubo
Author-email: s1922004@stu.musashino-u.ac.jp
License: UNKNOWN
Project-URL: Bug Tracker, https://github.com/sachan-37/Htraffick
Platform: UNKNOWN
Classifier: Programming Language :: Python :: 3
Classifier: License :: OSI Approved :: MIT License
Classifier: Operating System :: OS Independent
Requires-Python: >=3.9
